{
  "hero_name": "亚索",
  "hero_id": "157",
  "version": "16.8",
  "date": "2026-04-28 14:15:08",
  "lanes": {
    "support": {
      "win_rate": 39.51,
      "pick_rate": 0.0,
      "ban_rate": 0,
      "tier": "未知",
      "kda": 1.35,
      "kills": 4.4,
      "deaths": 10.0,
      "assists": 9.1,
      "total_games": 863,
      "core_items": [
        {
          "names": [
            "海妖杀手",
            "不朽盾弓",
            "无尽之刃"
          ],
          "item_ids": [
            "6672",
            "6673",
            "3031"
          ],
          "win_rate": 50.68,
          "pick_rate": 5.02,
          "games": 73
        },
        {
          "names": [
            "破败王者之刃",
            "不朽盾弓",
            "凡性的提醒"
          ],
          "item_ids": [
            "3153",
            "6673",
            "3033"
          ],
          "win_rate": 41.67,
          "pick_rate": 4.13,
          "games": 60
        },
        {
          "names": [
            "破败王者之刃",
            "不朽盾弓",
            "无尽之刃"
          ],
          "item_ids": [
            "3153",
            "6673",
            "3031"
          ],
          "win_rate": 49.15,
          "pick_rate": 4.06,
          "games": 59
        },
        {
          "names": [
            "海妖杀手",
            "不朽盾弓",
            "凡性的提醒"
          ],
          "item_ids": [
            "6672",
            "6673",
            "3033"
          ],
          "win_rate": 49.09,
          "pick_rate": 3.78,
          "games": 55
        },
        {
          "names": [
            "海妖杀手",
            "不朽盾弓",
            "多米尼克领主的致意"
          ],
          "item_ids": [
            "6672",
            "6673",
            "3036"
          ],
          "win_rate": 60.47,
          "pick_rate": 2.96,
          "games": 43
        }
      ],
      "boots": [
        {
          "names": [
            "狂战士胫甲"
          ],
          "item_ids": [
            "3006"
          ],
          "win_rate": 41.3,
          "pick_rate": 88.89,
          "games": 2649
        },
        {
          "names": [
            "铁板靴"
          ],
          "item_ids": [
            "3047"
          ],
          "win_rate": 43.2,
          "pick_rate": 5.67,
          "games": 169
        },
        {
          "names": [
            "水银之靴"
          ],
          "item_ids": [
            "3111"
          ],
          "win_rate": 38.36,
          "pick_rate": 4.9,
          "games": 146
        }
      ],
      "starting_items": [
        {
          "names": [
            "生命药水",
            "生命药水"
          ],
          "item_ids": [
            "2003",
            "2003"
          ],
          "win_rate": 41.32,
          "games": 2430
        },
        {
          "names": [
            "生命药水"
          ],
          "item_ids": [
            "2003"
          ],
          "win_rate": 39.89,
          "games": 188
        },
        {
          "names": [
            "多兰之刃",
            "生命药水"
          ],
          "item_ids": [
            "1055",
            "2003"
          ],
          "win_rate": 39.34,
          "games": 61
        }
      ],
      "skill_order": [
        {
          "order": "Q > E > W",
          "detail": "Q > E > W > Q > Q > R > Q > E > Q > E > R > E > E > W > W",
          "win_rate": 42.61,
          "pick_rate": 45.69
        },
        {
          "order": "Q > W > E",
          "detail": "Q > W > E > Q > Q > R > Q > W > Q > W > R > W > W > E > E",
          "win_rate": 41.14,
          "pick_rate": 28.1
        },
        {
          "order": "E > Q > W",
          "detail": "E > Q > W > E > E > R > E > Q > E > Q > R > Q > Q > W > W",
          "win_rate": 37.38,
          "pick_rate": 9.24
        }
      ],
      "runes": [
        {
          "name": "精密 + 坚决",
          "primary": true,
          "main": "精密",
          "vice": "坚决",
          "runes": [
            "致命节奏",
            "吸收生命力",
            "传说：欢欣",
            "坚毅不倒",
            "复苏之风",
            "过度生长",
            "攻击速度",
            "适应之力",
            "成长生命值"
          ],
          "rune_icons": [
            "https://game.gtimg.cn/images/lol/act/img/rune/LethalTempoTemp.png",
            "https://game.gtimg.cn/images/lol/act/img/rune/AbsorbLife.png",
            "https://game.gtimg.cn/images/lol/act/img/rune/LegendAlacrity.png",
            "https://game.gtimg.cn/images/lol/act/img/rune/LastStand.png",
            "https://game.gtimg.cn/images/lol/act/img/rune/SecondWind.png",
            "https://game.gtimg.cn/images/lol/act/img/rune/Overgrowth.png",
            "https://game.gtimg.cn/images/lol/act/img/rune/StatModsAttackSpeedIcon.png",
            "https://game.gtimg.cn/images/lol/act/img/rune/StatModsAdaptiveForceIcon.png",
            "https://game.gtimg.cn/images/lol/act/img/rune/StatModsHealthPlusIcon.png"
          ],
          "win_rate": 42.67,
          "pick_rate": 60.15,
          "games": 1795
        },
        {
          "name": "坚决 + 精密",
          "primary": true,
          "main": "坚决",
          "vice": "精密",
          "runes": [
            "不灭之握",
            "爆破",
            "复苏之风",
            "过度生长",
            "砍倒",
            "传说：欢欣",
            "攻击速度",
            "适应之力",
            "成长生命值"
          ],
          "rune_icons": [
            "https://game.gtimg.cn/images/lol/act/img/rune/GraspOfTheUndying.png",
            "https://game.gtimg.cn/images/lol/act/img/rune/Demolish.png",
            "https://game.gtimg.cn/images/lol/act/img/rune/SecondWind.png",
            "https://game.gtimg.cn/images/lol/act/img/rune/Overgrowth.png",
            "https://game.gtimg.cn/images/lol/act/img/rune/CutDown.png",
            "https://game.gtimg.cn/images/lol/act/img/rune/LegendAlacrity.png",
            "https://game.gtimg.cn/images/lol/act/img/rune/StatModsAttackSpeedIcon.png",
            "https://game.gtimg.cn/images/lol/act/img/rune/StatModsAdaptiveForceIcon.png",
            "https://game.gtimg.cn/images/lol/act/img/rune/StatModsHealthPlusIcon.png"
          ],
          "win_rate": 33.33,
          "pick_rate": 12.77,
          "games": 381
        },
        {
          "name": "精密 + 坚决",
          "primary": true,
          "main": "精密",
          "vice": "坚决",
          "runes": [
            "迅捷步法",
            "吸收生命力",
            "传说：欢欣",
            "坚毅不倒",
            "复苏之风",
            "过度生长",
            "攻击速度",
            "适应之力",
            "成长生命值"
          ],
          "rune_icons": [
            "https://game.gtimg.cn/images/lol/act/img/rune/FleetFootwork.png",
            "https://game.gtimg.cn/images/lol/act/img/rune/AbsorbLife.png",
            "https://game.gtimg.cn/images/lol/act/img/rune/LegendAlacrity.png",
            "https://game.gtimg.cn/images/lol/act/img/rune/LastStand.png",
            "https://game.gtimg.cn/images/lol/act/img/rune/SecondWind.png",
            "https://game.gtimg.cn/images/lol/act/img/rune/Overgrowth.png",
            "https://game.gtimg.cn/images/lol/act/img/rune/StatModsAttackSpeedIcon.png",
            "https://game.gtimg.cn/images/lol/act/img/rune/StatModsAdaptiveForceIcon.png",
            "https://game.gtimg.cn/images/lol/act/img/rune/StatModsHealthPlusIcon.png"
          ],
          "win_rate": 42.62,
          "pick_rate": 12.03,
          "games": 359
        }
      ],
      "spells": [
        {
          "names": [
            "闪现",
            "点燃"
          ],
          "ids": [
            "4",
            "14"
          ],
          "win_rate": 40.85,
          "pick_rate": 68.67
        },
        {
          "names": [
            "虚弱",
            "闪现"
          ],
          "ids": [
            "3",
            "4"
          ],
          "win_rate": 42.95,
          "pick_rate": 26.84
        }
      ]
    },
    "bottom": {
      "win_rate": 51.01,
      "pick_rate": 0.0,
      "ban_rate": 0,
      "tier": "未知",
      "kda": 1.94,
      "kills": 8.2,
      "deaths": 8.2,
      "assists": 7.8,
      "total_games": 2666,
      "core_items": [
        {
          "names": [
            "海妖杀手",
            "不朽盾弓",
            "无尽之刃"
          ],
          "item_ids": [
            "6672",
            "6673",
            "3031"
          ],
          "win_rate": 57.21,
          "pick_rate": 16.96,
          "games": 1096
        },
        {
          "names": [
            "海妖杀手",
            "不朽盾弓",
            "凡性的提醒"
          ],
          "item_ids": [
            "6672",
            "6673",
            "3033"
          ],
          "win_rate": 56.53,
          "pick_rate": 11.85,
          "games": 766
        },
        {
          "names": [
            "破败王者之刃",
            "不朽盾弓",
            "无尽之刃"
          ],
          "item_ids": [
            "3153",
            "6673",
            "3031"
          ],
          "win_rate": 55.26,
          "pick_rate": 7.64,
          "games": 494
        },
        {
          "names": [
            "海妖杀手",
            "不朽盾弓",
            "多米尼克领主的致意"
          ],
          "item_ids": [
            "6672",
            "6673",
            "3036"
          ],
          "win_rate": 59.55,
          "pick_rate": 7.53,
          "games": 487
        },
        {
          "names": [
            "破败王者之刃",
            "不朽盾弓",
            "凡性的提醒"
          ],
          "item_ids": [
            "3153",
            "6673",
            "3033"
          ],
          "win_rate": 52.65,
          "pick_rate": 4.67,
          "games": 302
        }
      ],
      "boots": [
        {
          "names": [
            "狂战士胫甲"
          ],
          "item_ids": [
            "3006"
          ],
          "win_rate": 50.6,
          "pick_rate": 93.82,
          "games": 7861
        },
        {
          "names": [
            "铁板靴"
          ],
          "item_ids": [
            "3047"
          ],
          "win_rate": 53.71,
          "pick_rate": 3.38,
          "games": 283
        },
        {
          "names": [
            "水银之靴"
          ],
          "item_ids": [
            "3111"
          ],
          "win_rate": 49.07,
          "pick_rate": 2.58,
          "games": 216
        }
      ],
      "starting_items": [
        {
          "names": [
            "多兰之刃",
            "生命药水"
          ],
          "item_ids": [
            "1055",
            "2003"
          ],
          "win_rate": 51.14,
          "games": 6277
        },
        {
          "names": [
            "多兰之盾",
            "生命药水"
          ],
          "item_ids": [
            "1054",
            "2003"
          ],
          "win_rate": 49.74,
          "games": 1713
        },
        {
          "names": [
            "萃取",
            "生命药水"
          ],
          "item_ids": [
            "1083",
            "2003"
          ],
          "win_rate": 33.33,
          "games": 33
        }
      ],
      "skill_order": [
        {
          "order": "Q > E > W",
          "detail": "Q > E > W > Q > Q > R > Q > E > Q > E > R > E > E > W > W",
          "win_rate": 50.4,
          "pick_rate": 46.8
        },
        {
          "order": "Q > W > E",
          "detail": "Q > W > E > Q > Q > R > Q > W > Q > W > R > W > W > E > E",
          "win_rate": 49.5,
          "pick_rate": 26.82
        },
        {
          "order": "E > Q > W",
          "detail": "E > Q > W > E > E > R > E > Q > E > Q > R > Q > Q > W > W",
          "win_rate": 51.86,
          "pick_rate": 9.25
        }
      ],
      "runes": [
        {
          "name": "精密 + 坚决",
          "primary": true,
          "main": "精密",
          "vice": "坚决",
          "runes": [
            "致命节奏",
            "吸收生命力",
            "传说：欢欣",
            "坚毅不倒",
            "复苏之风",
            "过度生长",
            "攻击速度",
            "适应之力",
            "成长生命值"
          ],
          "rune_icons": [
            "https://game.gtimg.cn/images/lol/act/img/rune/LethalTempoTemp.png",
            "https://game.gtimg.cn/images/lol/act/img/rune/AbsorbLife.png",
            "https://game.gtimg.cn/images/lol/act/img/rune/LegendAlacrity.png",
            "https://game.gtimg.cn/images/lol/act/img/rune/LastStand.png",
            "https://game.gtimg.cn/images/lol/act/img/rune/SecondWind.png",
            "https://game.gtimg.cn/images/lol/act/img/rune/Overgrowth.png",
            "https://game.gtimg.cn/images/lol/act/img/rune/StatModsAttackSpeedIcon.png",
            "https://game.gtimg.cn/images/lol/act/img/rune/StatModsAdaptiveForceIcon.png",
            "https://game.gtimg.cn/images/lol/act/img/rune/StatModsHealthPlusIcon.png"
          ],
          "win_rate": 51.42,
          "pick_rate": 78.75,
          "games": 6542
        },
        {
          "name": "精密 + 坚决",
          "primary": true,
          "main": "精密",
          "vice": "坚决",
          "runes": [
            "迅捷步法",
            "吸收生命力",
            "传说：欢欣",
            "坚毅不倒",
            "复苏之风",
            "过度生长",
            "攻击速度",
            "适应之力",
            "成长生命值"
          ],
          "rune_icons": [
            "https://game.gtimg.cn/images/lol/act/img/rune/FleetFootwork.png",
            "https://game.gtimg.cn/images/lol/act/img/rune/AbsorbLife.png",
            "https://game.gtimg.cn/images/lol/act/img/rune/LegendAlacrity.png",
            "https://game.gtimg.cn/images/lol/act/img/rune/LastStand.png",
            "https://game.gtimg.cn/images/lol/act/img/rune/SecondWind.png",
            "https://game.gtimg.cn/images/lol/act/img/rune/Overgrowth.png",
            "https://game.gtimg.cn/images/lol/act/img/rune/StatModsAttackSpeedIcon.png",
            "https://game.gtimg.cn/images/lol/act/img/rune/StatModsAdaptiveForceIcon.png",
            "https://game.gtimg.cn/images/lol/act/img/rune/StatModsHealthPlusIcon.png"
          ],
          "win_rate": 49.54,
          "pick_rate": 6.51,
          "games": 541
        },
        {
          "name": "精密 + 启迪",
          "primary": true,
          "main": "精密",
          "vice": "启迪",
          "runes": [
            "致命节奏",
            "凯旋",
            "传说：欢欣",
            "坚毅不倒",
            "返现",
            "饼干配送",
            "攻击速度",
            "适应之力",
            "生命值"
          ],
          "rune_icons": [
            "https://game.gtimg.cn/images/lol/act/img/rune/LethalTempoTemp.png",
            "https://game.gtimg.cn/images/lol/act/img/rune/Triumph.png",
            "https://game.gtimg.cn/images/lol/act/img/rune/LegendAlacrity.png",
            "https://game.gtimg.cn/images/lol/act/img/rune/LastStand.png",
            "https://game.gtimg.cn/images/lol/act/img/rune/CashBack2.png",
            "https://game.gtimg.cn/images/lol/act/img/rune/BiscuitDelivery.png",
            "https://game.gtimg.cn/images/lol/act/img/rune/StatModsAttackSpeedIcon.png",
            "https://game.gtimg.cn/images/lol/act/img/rune/StatModsAdaptiveForceIcon.png",
            "https://game.gtimg.cn/images/lol/act/img/rune/StatModsHealthScalingIcon.png"
          ],
          "win_rate": 50.94,
          "pick_rate": 5.13,
          "games": 426
        }
      ],
      "spells": [
        {
          "names": [
            "虚弱",
            "闪现"
          ],
          "ids": [
            "3",
            "4"
          ],
          "win_rate": 53.01,
          "pick_rate": 39.86
        },
        {
          "names": [
            "闪现",
            "点燃"
          ],
          "ids": [
            "4",
            "14"
          ],
          "win_rate": 47.42,
          "pick_rate": 37.32
        }
      ]
    },
    "mid": {
      "win_rate": 47.03,
      "pick_rate": 0.0,
      "ban_rate": 0,
      "tier": "未知",
      "kda": 1.61,
      "kills": 6.3,
      "deaths": 7.9,
      "assists": 6.4,
      "total_games": 74609,
      "core_items": [
        {
          "names": [
            "海妖杀手",
            "不朽盾弓",
            "无尽之刃"
          ],
          "item_ids": [
            "6672",
            "6673",
            "3031"
          ],
          "win_rate": 54.85,
          "pick_rate": 14.65,
          "games": 26728
        },
        {
          "names": [
            "破败王者之刃",
            "不朽盾弓",
            "凡性的提醒"
          ],
          "item_ids": [
            "3153",
            "6673",
            "3033"
          ],
          "win_rate": 52.58,
          "pick_rate": 11.73,
          "games": 21411
        },
        {
          "names": [
            "海妖杀手",
            "不朽盾弓",
            "凡性的提醒"
          ],
          "item_ids": [
            "6672",
            "6673",
            "3033"
          ],
          "win_rate": 53.01,
          "pick_rate": 10.5,
          "games": 19152
        },
        {
          "names": [
            "破败王者之刃",
            "不朽盾弓",
            "无尽之刃"
          ],
          "item_ids": [
            "3153",
            "6673",
            "3031"
          ],
          "win_rate": 55.63,
          "pick_rate": 7.78,
          "games": 14192
        },
        {
          "names": [
            "海妖杀手",
            "不朽盾弓",
            "多米尼克领主的致意"
          ],
          "item_ids": [
            "6672",
            "6673",
            "3036"
          ],
          "win_rate": 55.34,
          "pick_rate": 6.02,
          "games": 10984
        }
      ],
      "boots": [
        {
          "names": [
            "狂战士胫甲"
          ],
          "item_ids": [
            "3006"
          ],
          "win_rate": 46.84,
          "pick_rate": 90.62,
          "games": 263621
        },
        {
          "names": [
            "水银之靴"
          ],
          "item_ids": [
            "3111"
          ],
          "win_rate": 43.29,
          "pick_rate": 6.34,
          "games": 18435
        },
        {
          "names": [
            "铁板靴"
          ],
          "item_ids": [
            "3047"
          ],
          "win_rate": 46.46,
          "pick_rate": 2.75,
          "games": 8000
        }
      ],
      "starting_items": [
        {
          "names": [
            "多兰之刃",
            "生命药水"
          ],
          "item_ids": [
            "1055",
            "2003"
          ],
          "win_rate": 47.1,
          "games": 214418
        },
        {
          "names": [
            "多兰之盾",
            "生命药水"
          ],
          "item_ids": [
            "1054",
            "2003"
          ],
          "win_rate": 45.36,
          "games": 60066
        },
        {
          "names": [
            "萃取",
            "生命药水"
          ],
          "item_ids": [
            "1083",
            "2003"
          ],
          "win_rate": 45.73,
          "games": 1054
        }
      ],
      "skill_order": [
        {
          "order": "Q > E > W",
          "detail": "Q > E > W > Q > Q > R > Q > E > Q > E > R > E > E > W > W",
          "win_rate": 47.99,
          "pick_rate": 47.57
        },
        {
          "order": "Q > W > E",
          "detail": "Q > W > E > Q > Q > R > Q > W > Q > W > R > W > W > E > E",
          "win_rate": 46.13,
          "pick_rate": 26.5
        },
        {
          "order": "E > Q > W",
          "detail": "E > Q > W > E > E > R > E > Q > E > Q > R > Q > Q > W > W",
          "win_rate": 46.79,
          "pick_rate": 9.22
        }
      ],
      "runes": [
        {
          "name": "精密 + 坚决",
          "primary": true,
          "main": "精密",
          "vice": "坚决",
          "runes": [
            "致命节奏",
            "吸收生命力",
            "传说：欢欣",
            "坚毅不倒",
            "复苏之风",
            "过度生长",
            "攻击速度",
            "适应之力",
            "成长生命值"
          ],
          "rune_icons": [
            "https://game.gtimg.cn/images/lol/act/img/rune/LethalTempoTemp.png",
            "https://game.gtimg.cn/images/lol/act/img/rune/AbsorbLife.png",
            "https://game.gtimg.cn/images/lol/act/img/rune/LegendAlacrity.png",
            "https://game.gtimg.cn/images/lol/act/img/rune/LastStand.png",
            "https://game.gtimg.cn/images/lol/act/img/rune/SecondWind.png",
            "https://game.gtimg.cn/images/lol/act/img/rune/Overgrowth.png",
            "https://game.gtimg.cn/images/lol/act/img/rune/StatModsAttackSpeedIcon.png",
            "https://game.gtimg.cn/images/lol/act/img/rune/StatModsAdaptiveForceIcon.png",
            "https://game.gtimg.cn/images/lol/act/img/rune/StatModsHealthPlusIcon.png"
          ],
          "win_rate": 46.85,
          "pick_rate": 82.63,
          "games": 237672
        },
        {
          "name": "精密 + 坚决",
          "primary": true,
          "main": "精密",
          "vice": "坚决",
          "runes": [
            "迅捷步法",
            "吸收生命力",
            "传说：欢欣",
            "坚毅不倒",
            "复苏之风",
            "过度生长",
            "攻击速度",
            "适应之力",
            "成长生命值"
          ],
          "rune_icons": [
            "https://game.gtimg.cn/images/lol/act/img/rune/FleetFootwork.png",
            "https://game.gtimg.cn/images/lol/act/img/rune/AbsorbLife.png",
            "https://game.gtimg.cn/images/lol/act/img/rune/LegendAlacrity.png",
            "https://game.gtimg.cn/images/lol/act/img/rune/LastStand.png",
            "https://game.gtimg.cn/images/lol/act/img/rune/SecondWind.png",
            "https://game.gtimg.cn/images/lol/act/img/rune/Overgrowth.png",
            "https://game.gtimg.cn/images/lol/act/img/rune/StatModsAttackSpeedIcon.png",
            "https://game.gtimg.cn/images/lol/act/img/rune/StatModsAdaptiveForceIcon.png",
            "https://game.gtimg.cn/images/lol/act/img/rune/StatModsHealthPlusIcon.png"
          ],
          "win_rate": 45.2,
          "pick_rate": 7.02,
          "games": 20206
        },
        {
          "name": "坚决 + 精密",
          "primary": true,
          "main": "坚决",
          "vice": "精密",
          "runes": [
            "不灭之握",
            "爆破",
            "复苏之风",
            "过度生长",
            "砍倒",
            "传说：欢欣",
            "攻击速度",
            "适应之力",
            "成长生命值"
          ],
          "rune_icons": [
            "https://game.gtimg.cn/images/lol/act/img/rune/GraspOfTheUndying.png",
            "https://game.gtimg.cn/images/lol/act/img/rune/Demolish.png",
            "https://game.gtimg.cn/images/lol/act/img/rune/SecondWind.png",
            "https://game.gtimg.cn/images/lol/act/img/rune/Overgrowth.png",
            "https://game.gtimg.cn/images/lol/act/img/rune/CutDown.png",
            "https://game.gtimg.cn/images/lol/act/img/rune/LegendAlacrity.png",
            "https://game.gtimg.cn/images/lol/act/img/rune/StatModsAttackSpeedIcon.png",
            "https://game.gtimg.cn/images/lol/act/img/rune/StatModsAdaptiveForceIcon.png",
            "https://game.gtimg.cn/images/lol/act/img/rune/StatModsHealthPlusIcon.png"
          ],
          "win_rate": 45.09,
          "pick_rate": 4.56,
          "games": 13104
        }
      ],
      "spells": [
        {
          "names": [
            "闪现",
            "点燃"
          ],
          "ids": [
            "4",
            "14"
          ],
          "win_rate": 46.31,
          "pick_rate": 79.27
        },
        {
          "names": [
            "虚弱",
            "闪现"
          ],
          "ids": [
            "3",
            "4"
          ],
          "win_rate": 48.99,
          "pick_rate": 14.46
        }
      ]
    },
    "top": {
      "win_rate": 49.1,
      "pick_rate": 0.0,
      "ban_rate": 0,
      "tier": "未知",
      "kda": 1.62,
      "kills": 6.7,
      "deaths": 7.9,
      "assists": 6.1,
      "total_games": 13162,
      "core_items": [
        {
          "names": [
            "海妖杀手",
            "不朽盾弓",
            "无尽之刃"
          ],
          "item_ids": [
            "6672",
            "6673",
            "3031"
          ],
          "win_rate": 57.61,
          "pick_rate": 13.36,
          "games": 4352
        },
        {
          "names": [
            "破败王者之刃",
            "不朽盾弓",
            "凡性的提醒"
          ],
          "item_ids": [
            "3153",
            "6673",
            "3033"
          ],
          "win_rate": 56.3,
          "pick_rate": 11.59,
          "games": 3776
        },
        {
          "names": [
            "海妖杀手",
            "不朽盾弓",
            "凡性的提醒"
          ],
          "item_ids": [
            "6672",
            "6673",
            "3033"
          ],
          "win_rate": 53.43,
          "pick_rate": 10.64,
          "games": 3466
        },
        {
          "names": [
            "破败王者之刃",
            "不朽盾弓",
            "无尽之刃"
          ],
          "item_ids": [
            "3153",
            "6673",
            "3031"
          ],
          "win_rate": 57.76,
          "pick_rate": 7.84,
          "games": 2552
        },
        {
          "names": [
            "海妖杀手",
            "不朽盾弓",
            "多米尼克领主的致意"
          ],
          "item_ids": [
            "6672",
            "6673",
            "3036"
          ],
          "win_rate": 59.22,
          "pick_rate": 6.56,
          "games": 2136
        }
      ],
      "boots": [
        {
          "names": [
            "狂战士胫甲"
          ],
          "item_ids": [
            "3006"
          ],
          "win_rate": 48.82,
          "pick_rate": 91.14,
          "games": 45406
        },
        {
          "names": [
            "水银之靴"
          ],
          "item_ids": [
            "3111"
          ],
          "win_rate": 46.9,
          "pick_rate": 4.6,
          "games": 2290
        },
        {
          "names": [
            "铁板靴"
          ],
          "item_ids": [
            "3047"
          ],
          "win_rate": 45.68,
          "pick_rate": 3.99,
          "games": 1990
        }
      ],
      "starting_items": [
        {
          "names": [
            "多兰之刃",
            "生命药水"
          ],
          "item_ids": [
            "1055",
            "2003"
          ],
          "win_rate": 49.1,
          "games": 37440
        },
        {
          "names": [
            "多兰之盾",
            "生命药水"
          ],
          "item_ids": [
            "1054",
            "2003"
          ],
          "win_rate": 46.98,
          "games": 9560
        },
        {
          "names": [
            "萃取",
            "生命药水"
          ],
          "item_ids": [
            "1083",
            "2003"
          ],
          "win_rate": 43.01,
          "games": 193
        }
      ],
      "skill_order": [
        {
          "order": "Q > E > W",
          "detail": "Q > E > W > Q > Q > R > Q > E > Q > E > R > E > E > W > W",
          "win_rate": 49.63,
          "pick_rate": 47.63
        },
        {
          "order": "Q > W > E",
          "detail": "Q > W > E > Q > Q > R > Q > W > Q > W > R > W > W > E > E",
          "win_rate": 48.08,
          "pick_rate": 26.59
        },
        {
          "order": "E > Q > W",
          "detail": "E > Q > W > E > E > R > E > Q > E > Q > R > Q > Q > W > W",
          "win_rate": 48.79,
          "pick_rate": 9.17
        }
      ],
      "runes": [
        {
          "name": "精密 + 坚决",
          "primary": true,
          "main": "精密",
          "vice": "坚决",
          "runes": [
            "致命节奏",
            "吸收生命力",
            "传说：欢欣",
            "坚毅不倒",
            "复苏之风",
            "过度生长",
            "攻击速度",
            "适应之力",
            "成长生命值"
          ],
          "rune_icons": [
            "https://game.gtimg.cn/images/lol/act/img/rune/LethalTempoTemp.png",
            "https://game.gtimg.cn/images/lol/act/img/rune/AbsorbLife.png",
            "https://game.gtimg.cn/images/lol/act/img/rune/LegendAlacrity.png",
            "https://game.gtimg.cn/images/lol/act/img/rune/LastStand.png",
            "https://game.gtimg.cn/images/lol/act/img/rune/SecondWind.png",
            "https://game.gtimg.cn/images/lol/act/img/rune/Overgrowth.png",
            "https://game.gtimg.cn/images/lol/act/img/rune/StatModsAttackSpeedIcon.png",
            "https://game.gtimg.cn/images/lol/act/img/rune/StatModsAdaptiveForceIcon.png",
            "https://game.gtimg.cn/images/lol/act/img/rune/StatModsHealthPlusIcon.png"
          ],
          "win_rate": 48.84,
          "pick_rate": 83.25,
          "games": 40978
        },
        {
          "name": "精密 + 坚决",
          "primary": true,
          "main": "精密",
          "vice": "坚决",
          "runes": [
            "迅捷步法",
            "吸收生命力",
            "传说：欢欣",
            "坚毅不倒",
            "复苏之风",
            "过度生长",
            "攻击速度",
            "适应之力",
            "成长生命值"
          ],
          "rune_icons": [
            "https://game.gtimg.cn/images/lol/act/img/rune/FleetFootwork.png",
            "https://game.gtimg.cn/images/lol/act/img/rune/AbsorbLife.png",
            "https://game.gtimg.cn/images/lol/act/img/rune/LegendAlacrity.png",
            "https://game.gtimg.cn/images/lol/act/img/rune/LastStand.png",
            "https://game.gtimg.cn/images/lol/act/img/rune/SecondWind.png",
            "https://game.gtimg.cn/images/lol/act/img/rune/Overgrowth.png",
            "https://game.gtimg.cn/images/lol/act/img/rune/StatModsAttackSpeedIcon.png",
            "https://game.gtimg.cn/images/lol/act/img/rune/StatModsAdaptiveForceIcon.png",
            "https://game.gtimg.cn/images/lol/act/img/rune/StatModsHealthPlusIcon.png"
          ],
          "win_rate": 48.46,
          "pick_rate": 5.69,
          "games": 2800
        },
        {
          "name": "坚决 + 精密",
          "primary": true,
          "main": "坚决",
          "vice": "精密",
          "runes": [
            "不灭之握",
            "爆破",
            "复苏之风",
            "过度生长",
            "砍倒",
            "传说：欢欣",
            "攻击速度",
            "适应之力",
            "成长生命值"
          ],
          "rune_icons": [
            "https://game.gtimg.cn/images/lol/act/img/rune/GraspOfTheUndying.png",
            "https://game.gtimg.cn/images/lol/act/img/rune/Demolish.png",
            "https://game.gtimg.cn/images/lol/act/img/rune/SecondWind.png",
            "https://game.gtimg.cn/images/lol/act/img/rune/Overgrowth.png",
            "https://game.gtimg.cn/images/lol/act/img/rune/CutDown.png",
            "https://game.gtimg.cn/images/lol/act/img/rune/LegendAlacrity.png",
            "https://game.gtimg.cn/images/lol/act/img/rune/StatModsAttackSpeedIcon.png",
            "https://game.gtimg.cn/images/lol/act/img/rune/StatModsAdaptiveForceIcon.png",
            "https://game.gtimg.cn/images/lol/act/img/rune/StatModsHealthPlusIcon.png"
          ],
          "win_rate": 45.93,
          "pick_rate": 5.34,
          "games": 2628
        }
      ],
      "spells": [
        {
          "names": [
            "闪现",
            "点燃"
          ],
          "ids": [
            "4",
            "14"
          ],
          "win_rate": 48.66,
          "pick_rate": 74.02
        },
        {
          "names": [
            "虚弱",
            "闪现"
          ],
          "ids": [
            "3",
            "4"
          ],
          "win_rate": 49.32,
          "pick_rate": 19.58
        }
      ]
    },
    "jungle": {
      "win_rate": 0,
      "pick_rate": 0.0,
      "ban_rate": 0,
      "tier": "未知",
      "kda": 0.0,
      "kills": 0.0,
      "deaths": 0.0,
      "assists": 0.0,
      "total_games": 0,
      "core_items": [],
      "boots": [],
      "starting_items": [],
      "skill_order": [],
      "runes": [],
      "spells": []
    }
  },
  "counter": {
    "strong_against": [],
    "weak_against": [
      {
        "hero_name": "玛尔扎哈",
        "hero_id": "90",
        "win_rate": 41.2,
        "alias": "Malzahar",
        "reason": "被技能机制克制"
      },
      {
        "hero_name": "普朗克",
        "hero_id": "41",
        "win_rate": 46.68,
        "alias": "Gangplank",
        "reason": "对线劣势"
      }
    ],
    "source": "tencent_official"
  },
  "source": "tencent_official",
  "timestamp": 1777358098.3986924,
  "win_rate": {
    "hero_name": "亚索",
    "overall": {
      "win_rate": 49.1,
      "pick_rate": 0.0,
      "ban_rate": 0,
      "tier": "未知",
      "kda": 1.62
    },
    "source": "tencent_official",
    "timestamp": 1777358098.4058678
  },
  "build": {
    "hero_name": "亚索",
    "position": "top",
    "core_items": [
      {
        "names": [
          "海妖杀手",
          "不朽盾弓",
          "无尽之刃"
        ],
        "item_ids": [
          "6672",
          "6673",
          "3031"
        ],
        "win_rate": 57.61,
        "pick_rate": 13.36,
        "games": 4352
      },
      {
        "names": [
          "破败王者之刃",
          "不朽盾弓",
          "凡性的提醒"
        ],
        "item_ids": [
          "3153",
          "6673",
          "3033"
        ],
        "win_rate": 56.3,
        "pick_rate": 11.59,
        "games": 3776
      },
      {
        "names": [
          "海妖杀手",
          "不朽盾弓",
          "凡性的提醒"
        ],
        "item_ids": [
          "6672",
          "6673",
          "3033"
        ],
        "win_rate": 53.43,
        "pick_rate": 10.64,
        "games": 3466
      },
      {
        "names": [
          "破败王者之刃",
          "不朽盾弓",
          "无尽之刃"
        ],
        "item_ids": [
          "3153",
          "6673",
          "3031"
        ],
        "win_rate": 57.76,
        "pick_rate": 7.84,
        "games": 2552
      },
      {
        "names": [
          "海妖杀手",
          "不朽盾弓",
          "多米尼克领主的致意"
        ],
        "item_ids": [
          "6672",
          "6673",
          "3036"
        ],
        "win_rate": 59.22,
        "pick_rate": 6.56,
        "games": 2136
      }
    ],
    "boots": [
      {
        "names": [
          "狂战士胫甲"
        ],
        "item_ids": [
          "3006"
        ],
        "win_rate": 48.82,
        "pick_rate": 91.14,
        "games": 45406
      },
      {
        "names": [
          "水银之靴"
        ],
        "item_ids": [
          "3111"
        ],
        "win_rate": 46.9,
        "pick_rate": 4.6,
        "games": 2290
      },
      {
        "names": [
          "铁板靴"
        ],
        "item_ids": [
          "3047"
        ],
        "win_rate": 45.68,
        "pick_rate": 3.99,
        "games": 1990
      }
    ],
    "starting_items": [
      {
        "names": [
          "多兰之刃",
          "生命药水"
        ],
        "item_ids": [
          "1055",
          "2003"
        ],
        "win_rate": 49.1,
        "games": 37440
      },
      {
        "names": [
          "多兰之盾",
          "生命药水"
        ],
        "item_ids": [
          "1054",
          "2003"
        ],
        "win_rate": 46.98,
        "games": 9560
      },
      {
        "names": [
          "萃取",
          "生命药水"
        ],
        "item_ids": [
          "1083",
          "2003"
        ],
        "win_rate": 43.01,
        "games": 193
      }
    ],
    "skill_order": [
      {
        "order": "Q > E > W",
        "detail": "Q > E > W > Q > Q > R > Q > E > Q > E > R > E > E > W > W",
        "win_rate": 49.63,
        "pick_rate": 47.63
      },
      {
        "order": "Q > W > E",
        "detail": "Q > W > E > Q > Q > R > Q > W > Q > W > R > W > W > E > E",
        "win_rate": 48.08,
        "pick_rate": 26.59
      },
      {
        "order": "E > Q > W",
        "detail": "E > Q > W > E > E > R > E > Q > E > Q > R > Q > Q > W > W",
        "win_rate": 48.79,
        "pick_rate": 9.17
      }
    ],
    "runes": [
      {
        "name": "精密 + 坚决",
        "primary": true,
        "main": "精密",
        "vice": "坚决",
        "runes": [
          "致命节奏",
          "吸收生命力",
          "传说：欢欣",
          "坚毅不倒",
          "复苏之风",
          "过度生长",
          "攻击速度",
          "适应之力",
          "成长生命值"
        ],
        "rune_icons": [
          "https://game.gtimg.cn/images/lol/act/img/rune/LethalTempoTemp.png",
          "https://game.gtimg.cn/images/lol/act/img/rune/AbsorbLife.png",
          "https://game.gtimg.cn/images/lol/act/img/rune/LegendAlacrity.png",
          "https://game.gtimg.cn/images/lol/act/img/rune/LastStand.png",
          "https://game.gtimg.cn/images/lol/act/img/rune/SecondWind.png",
          "https://game.gtimg.cn/images/lol/act/img/rune/Overgrowth.png",
          "https://game.gtimg.cn/images/lol/act/img/rune/StatModsAttackSpeedIcon.png",
          "https://game.gtimg.cn/images/lol/act/img/rune/StatModsAdaptiveForceIcon.png",
          "https://game.gtimg.cn/images/lol/act/img/rune/StatModsHealthPlusIcon.png"
        ],
        "win_rate": 48.84,
        "pick_rate": 83.25,
        "games": 40978
      },
      {
        "name": "精密 + 坚决",
        "primary": true,
        "main": "精密",
        "vice": "坚决",
        "runes": [
          "迅捷步法",
          "吸收生命力",
          "传说：欢欣",
          "坚毅不倒",
          "复苏之风",
          "过度生长",
          "攻击速度",
          "适应之力",
          "成长生命值"
        ],
        "rune_icons": [
          "https://game.gtimg.cn/images/lol/act/img/rune/FleetFootwork.png",
          "https://game.gtimg.cn/images/lol/act/img/rune/AbsorbLife.png",
          "https://game.gtimg.cn/images/lol/act/img/rune/LegendAlacrity.png",
          "https://game.gtimg.cn/images/lol/act/img/rune/LastStand.png",
          "https://game.gtimg.cn/images/lol/act/img/rune/SecondWind.png",
          "https://game.gtimg.cn/images/lol/act/img/rune/Overgrowth.png",
          "https://game.gtimg.cn/images/lol/act/img/rune/StatModsAttackSpeedIcon.png",
          "https://game.gtimg.cn/images/lol/act/img/rune/StatModsAdaptiveForceIcon.png",
          "https://game.gtimg.cn/images/lol/act/img/rune/StatModsHealthPlusIcon.png"
        ],
        "win_rate": 48.46,
        "pick_rate": 5.69,
        "games": 2800
      },
      {
        "name": "坚决 + 精密",
        "primary": true,
        "main": "坚决",
        "vice": "精密",
        "runes": [
          "不灭之握",
          "爆破",
          "复苏之风",
          "过度生长",
          "砍倒",
          "传说：欢欣",
          "攻击速度",
          "适应之力",
          "成长生命值"
        ],
        "rune_icons": [
          "https://game.gtimg.cn/images/lol/act/img/rune/GraspOfTheUndying.png",
          "https://game.gtimg.cn/images/lol/act/img/rune/Demolish.png",
          "https://game.gtimg.cn/images/lol/act/img/rune/SecondWind.png",
          "https://game.gtimg.cn/images/lol/act/img/rune/Overgrowth.png",
          "https://game.gtimg.cn/images/lol/act/img/rune/CutDown.png",
          "https://game.gtimg.cn/images/lol/act/img/rune/LegendAlacrity.png",
          "https://game.gtimg.cn/images/lol/act/img/rune/StatModsAttackSpeedIcon.png",
          "https://game.gtimg.cn/images/lol/act/img/rune/StatModsAdaptiveForceIcon.png",
          "https://game.gtimg.cn/images/lol/act/img/rune/StatModsHealthPlusIcon.png"
        ],
        "win_rate": 45.93,
        "pick_rate": 5.34,
        "games": 2628
      }
    ],
    "spells": [
      {
        "names": [
          "闪现",
          "点燃"
        ],
        "ids": [
          "4",
          "14"
        ],
        "win_rate": 48.66,
        "pick_rate": 74.02
      },
      {
        "names": [
          "虚弱",
          "闪现"
        ],
        "ids": [
          "3",
          "4"
        ],
        "win_rate": 49.32,
        "pick_rate": 19.58
      }
    ],
    "source": "tencent_official",
    "timestamp": 1777358098.4058678
  },
  "wanplus": {
    "hero_name": "亚索",
    "role": "战士、刺客",
    "difficulty": 10,
    "strengths": [],
    "weaknesses": [],
    "combo_tips": "",
    "source": "tencent_official",
    "timestamp": 1777358098.4058678
  }
}